tmp/build/u337mg096_ece337_signed_multiplier_1.0.0/sim-modelsim/src/u337mg096_ece337_signed_multiplier_1.0.0/source/signed_multiplier.sv
`timescale 1ns / 10ps
module signed_multiplier(
    input  logic signed [7:0] weight,
    input  logic signed [7:0] value,
    input  logic signed [7:0] cumulative,
    input  logic float,
    output logic signed [7:0] out,
    output logic overflow
);
    // partial sums logics
    logic signed [15:0] extended_weight;
    logic signed [15:0] partial0;
    logic signed [15:0] partial1;
    logic signed [15:0] partial2;
    logic signed [15:0] partial3;
    logic signed [15:0] partial4;
    logic signed [15:0] partial5;
    logic signed [15:0] partial6;
    logic signed [15:0] partial7;

    logic signed [15:0] product;
    logic signed [15:0] sum_extended;

    // floating point logics
    logic sign_cumulative, sign_weight, sign_value, sign_product;
    logic [3:0] exponent_cumulative, exponent_weight, exponent_value;
    logic [4:0] exponent_product;
    logic [3:0] man_cumulative, man_weight, man_value, man_out;
    logic [3:0] man_product;

    // signs
    assign sign_cumulative = cumulative[7];
    assign sign_weight = weight[7];
    assign sign_value = value[7];
    assign sign_product = sign_value ^ sign_weight;
    
    // exponents
    assign exponent_cumulative = cumulative[6:3];
    assign exponent_weight = weight[6:3];
    assign exponent_value = value[6:3];
    
    // implicit 1 in front of mantissa
    assign man_cumulative = {1'b1, cumulative[2:0]};
    assign man_weight = {1'b1, weight[2:0]};
    assign man_value = {1'b1, value[2:0]};


    // sign extend
    assign extended_weight = {{8{weight[7]}}, weight};
    always_comb begin
        if(!float) begin

            // partials ials that are "ands" of a value bit and all the weight bits. creates shifted versions to add
            partial0 = value[0] ? (extended_weight) : 16'sd0;
            partial1 = value[1] ? (extended_weight << 1) : 16'sd0;
            partial2 = value[2] ? (extended_weight << 2) : 16'sd0;
            partial3 = value[3] ? (extended_weight << 3) : 16'sd0;
            partial4 = value[4] ? (extended_weight << 4) : 16'sd0;
            partial5 = value[5] ? (extended_weight << 5) : 16'sd0;
            partial6 = value[6] ? (extended_weight << 6) : 16'sd0;
            partial7 = value[7] ? (extended_weight << 7) : 16'sd0;

            product = partial0 + partial1 + partial2 + partial3 +
            partial4 + partial5 + partial6 + partial7;
        
        end
        else begin
            // {15'h00, sign_value ^ sign_weight};
            
            partial0 = man_value[0] ? {12'h00, (man_weight)}:16'sd0;
            partial1 = man_value[1] ? {11'h00, (man_weight), 1'b0}:16'sd0;
            partial2 = man_value[2] ? {10'h00, (man_weight) , 2'b00}:16'sd0;
            partial3 = man_value[3] ? {9'h00, (man_weight), 3'b000}: 16'sd0;
            partial4 = 0;
            partial5 = 0;
            partial6 = 0;
            partial7 = 0;
            product = partial0 + partial1 + partial2 + partial3;

            
        end
    end

    always_comb begin
        if(!float) begin
            sum_extended = product + {{8{cumulative[7]}}, cumulative};
            exponent_product = 0;
            man_product = 0;
        end
        else begin
            if(product[7]) begin
                if(exponent_weight <= 4'd6 || exponent_value <= 4'd6) begin
                    exponent_product = 5'd7;
                    man_product = 0;
                end
                else begin
                    exponent_product = exponent_weight + exponent_value - 4'd6;
                    // this acts as both truncate and normalize step.
                    man_product = {1'b1,product[6:4]};
                end
            end
            else if(product[6]) begin
                if(exponent_weight <= 4'd6 || exponent_value <= 4'd6) begin
                    exponent_product = 5'd7;
                    man_product = 0;
                end
                else begin
                    exponent_product = exponent_weight + exponent_value - 4'd7;
                    man_product = {1'b1, product[5:3]};
                end
                
            end
            else if(product[5]) begin
                if(exponent_weight <= 4'd6 || exponent_value <= 4'd6) begin
                    exponent_product = 5'd7;
                    man_product = 0;
                end
                else begin
                    exponent_product = exponent_weight + exponent_value - 4'd8;
                    man_product = {1'b1, product[4:2]};
                end
                
            end
            else if(product[4]) begin
                if(exponent_weight <= 4'd6 || exponent_value <= 4'd6) begin
                    exponent_product = 5'd9;
                    man_product = 0;
                end
                else begin
                    exponent_product = exponent_weight + exponent_value - 4'd9;
                    man_product = {1'b1, product[3:1]};
                end
                
            end
            else begin
                if(exponent_weight <= 4'd6 || exponent_value <= 4'd6) begin
                    exponent_product = 5'd10;
                    man_product = 0;
                end
                else begin
                    exponent_product = exponent_weight + exponent_value - 4'd10;
                    man_product = {1'b1, product[2:0]};
                end
                
            end
            sum_extended = 0;
            
        end
    end


    // logics to add cumulative to the float
    logic [3:0] final_exp;
    logic [4:0] man_sum;
    logic [3:0] m_large;
    logic [3:0] m_small;
    logic s_small;
    logic s_large;
    logic [4:0] e_diff;
    logic [3:0] e_out;
    
    always_comb begin
        if (exponent_product >= exponent_cumulative) begin
            final_exp = exponent_product;
            e_diff = exponent_product - exponent_cumulative;
            m_large = man_product;
            if(exponent_cumulative <= 4'd6) begin
                m_small = 0;
            end
            else begin
                m_small = man_cumulative >> e_diff;
            end
            s_large = sign_product;
            s_small = sign_cumulative;
        end else begin
            final_exp = exponent_cumulative;
            e_diff = exponent_cumulative - exponent_product;
            m_large = man_cumulative;
            if(exponent_product <= 4'd6) begin
                m_small = 0;
            end
            else begin
                m_small = man_product >> e_diff;
            end

            s_large = sign_cumulative;
            s_small = sign_product;
        end
    end

    always_comb begin
        if (s_large == s_small)
            man_sum = m_large + m_small;
        else begin
            if (m_large >= m_small)
                man_sum = m_large - m_small;
            else
                man_sum = m_small - m_large;
        end

    end
    logic s_out;
    assign s_out = (m_large >= m_small) ? s_large : s_small;

    // saturate
    always_comb begin
        if(!float) begin
            if (sum_extended >= 16'sd127 && (!sum_extended[15])) begin
                out = 8'sh7F;
                overflow = 1;
            end
            else if (sum_extended <= -16'sd128 && sum_extended[15]) begin
                out = 8'sh80;
                overflow = 1;
            end
            else begin
                out = sum_extended[7:0];
                overflow = 0;
            end
            man_out = 0;
            e_out = 0;
        end
        else begin
            if (man_sum[4]) begin
                overflow = 1;
                man_out = {1'b1,man_sum[3:1] + 1};
                e_out = final_exp + 1;
            end 
            else if (man_sum[3]) begin
                overflow = 0;
                man_out = {1'b1,man_sum[2:0]};
                e_out = final_exp;
            end
            else if (man_sum[2]) begin
                overflow = 0;
                man_out = {1'b1,man_sum[1:0],1'b0};
                e_out = final_exp - 1;
            end
            else if (man_sum[1]) begin
                overflow = 0;
                man_out = {1'b1, man_sum[0],2'b00};
                e_out = final_exp - 2;
            end
            else begin
                overflow = 0;
                man_out = {1'b1,3'b0};
                e_out = final_exp - 3;
            end
            out = {s_out, e_out, man_out[2:0]};

        end
    end

endmodule

tmp/build/u337mg096_ece337_signed_multiplier_1.0.0/sim-modelsim/src/u337mg096_ece337_signed_multiplier_1.0.0/testbench/tb_signed_multiplier.sv
`timescale 1ns / 10ps
/* verilator coverage_off */

module tb_signed_multiplier ();

    localparam CLK_PERIOD = 10ns;

    initial begin
        $dumpfile("waveform.vcd");
        $dumpvars;
    end

    logic clk, n_rst;

    // clockgen
    always begin
        clk = 0;
        #(CLK_PERIOD / 2.0);
        clk = 1;
        #(CLK_PERIOD / 2.0);
    end

    task reset_dut;
    begin
        n_rst = 0;
        @(posedge clk);
        @(posedge clk);
        @(negedge clk);
        n_rst = 1;
        @(posedge clk);
        @(posedge clk);
    end
    endtask

    logic signed [7:0] weight;
    logic signed [7:0] value;
    logic signed [7:0] cumulative;
    logic float;
    logic signed [7:0] out;
    logic overflow;
    logic load;

    signed_multiplier #() DUT (.weight(weight), .value(value), .cumulative(cumulative), .float(float), .out(out), .overflow(overflow));

    task one_int_result;
    input logic [7:0] w;
    input logic [7:0] v;
    input logic [7:0] c;
    begin
        weight = w;
        value = v;
        cumulative = c;
        float = 0;
        #10;
        $display("p0: %d", out);
        #25;
    end
    endtask

 task fp8_to_real;
    input  logic [7:0] fp8;
    output real        val;
    logic  sign;
    logic signed [3:0] exp;   
    logic [2:0] mant;
    int   E;
    real  M;
    begin
        sign = fp8[7];
        exp  = fp8[6:3];       
        mant = fp8[2:0];

        if (exp <= 4'd6) begin // subnormals
            M = 0;
            E = 0; 
            val = 0.0;
        end else begin
            M = (8 + mant) / 8.0;
            E = exp - 4'd7;       
            val = (sign ? -1.0 : +1.0) * M * (2.0 ** E);
        end

    end
endtask
    
    task one_float_result;
    input logic [7:0] w;
    input logic [7:0] v;
    input logic [7:0] c;
    real real_weight;
    real real_value;
    real real_cumulative;
    real real_out;
    begin
        weight = w;
        value = v;
        cumulative = c;
        float = 1;
        #10;
        fp8_to_real(.fp8(w), .val(real_weight));
        fp8_to_real(.fp8(v), .val(real_value));
        fp8_to_real(.fp8(c), .val(real_cumulative));
        fp8_to_real(.fp8(out), .val(real_out));

        if((real_weight * real_value) + real_cumulative != real_out) begin
            $display("Failed float mult w:%h, v:%h", weight, value);
        end
        $display("float mult w:%h, v:%h, c:%h, o:%h", weight, value, cumulative, out);
        #25;
    end
    endtask

    int fail_count;
    
    task test_multiplication_int;
    input int seed;
    real real_weight;
    real real_value;
    real real_cumulative;
    real real_out;
    begin
        for(int i = 0; i<1000; i++) begin
            weight =     $random(seed);
            value =      $random(seed);
            cumulative = $random(seed);
            float = 0;
            #10;
            // fp8_to_real(.fp8(w), .val(real_weight));
            // fp8_to_real(.fp8(v), .val(real_value));
            // fp8_to_real(.fp8(c), .val(real_cumulative));
            // fp8_to_real(.fp8(out), .val(real_out));
    
            if(out != (weight * value) + cumulative) begin
                if((out == 8'h80 || out == 8'h7f) && overflow) begin
                end
                else begin
                    fail_count += 1;
                    $display("failed mult weight:%h, value:%h, cumulative:%h, out:%h", weight, value, cumulative, out);
                end
            end
            // if((real_weight * real_value) + real_cumulative != real_out) begin
            //     $display("Failed float mult w:%h, v:%h", weight, value);
            // end
            // $display("float mult w:%h, v:%h, c:%h, o:%h", weight, value, cumulative, out);
            #25;
        end
    end
    endtask

    task test_multiplication_float;
    input int seed;
    real real_weight;
    real real_value;
    real real_cumulative;
    real real_out;
    logic [7:0] random_byte;
    static real error_allowed = 0.5;
    static real diff;
    begin
        for(int i = 0; i<500; i++) begin
            random_byte = {$urandom_range(70,32)};
            weight =     {random_byte};
            random_byte = {$urandom_range(70,32)};
            value =      {random_byte};
            random_byte = {$urandom_range(70,32)};
            cumulative = {random_byte};
            float = 1;
            #10;
            fp8_to_real(.fp8(weight), .val(real_weight));
            fp8_to_real(.fp8(value), .val(real_value));
            fp8_to_real(.fp8(cumulative), .val(real_cumulative));
            fp8_to_real(.fp8(out), .val(real_out));
    
            // if(out != (weight * value) + cumulative) begin
            //     $display("failed mult weight:%h, value:%h, cumulative:%h, out:%h", weight, value, cumulative, out);
            // end
            diff = (real_weight * real_value) + real_cumulative - real_out;
            if(diff > error_allowed || diff < -error_allowed) begin
                fail_count += 1;
                $display("Failed float mult w:%h, v:%h, expected:%d, real_weight:%d, real_value:%d, real_cumulative:%d, real_out:%d", weight, value, (real_weight * real_value) + real_cumulative, real_weight, real_value, real_cumulative, real_out);
            end
            // $display("float mult w:%h, v:%h, c:%h, o:%h", weight, value, cumulative, out);
            #25;
        end
        for(int i = 0; i<500; i++) begin
            random_byte = {$urandom_range(128,64)};
            weight =     {1'b1, random_byte[7:1]};
            random_byte = {$urandom_range(128,64)};
            value =      {1'b1, random_byte[7:1]};
            // random_byte = {$urandom_range(128,64)};
            // cumulative = {1'b1, random_byte[7:1]};
            random_byte = {$urandom_range(64,32)};
            cumulative = {random_byte};
            float = 1;
            #10;
            fp8_to_real(.fp8(weight), .val(real_weight));
            fp8_to_real(.fp8(value), .val(real_value));
            fp8_to_real(.fp8(cumulative), .val(real_cumulative));
            fp8_to_real(.fp8(out), .val(real_out));
    
            // if(out != (weight * value) + cumulative) begin
            //     $display("failed mult weight:%h, value:%h, cumulative:%h, out:%h", weight, value, cumulative, out);
            // end
            diff = (real_weight * real_value) + real_cumulative - real_out;
            if(diff > error_allowed || diff < -error_allowed) begin
                fail_count += 1;
                $display("Failed float mult w:%h, v:%h, expected:%d, real_weight:%d, real_value:%d, real_cumulative:%d, real_out:%d", weight, value, (real_weight * real_value) + real_cumulative, real_weight, real_value, real_cumulative, real_out);
            end
            // $display("float mult w:%h, v:%h, c:%h, o:%h", weight, value, cumulative, out);
            #25;
        end
    end
    endtask


    initial begin
        n_rst = 1;

        reset_dut;
        load = 0;
        test_multiplication_int(.seed(1129));
        load = 1;
        #250;
        load = 0;
        test_multiplication_float(.seed(9151));
        #250;

        $display("\n=========================================================");
        $display("               TOTAL FAILED TESTS  = %0d", fail_count);
        $display("=========================================================\n");

        $finish;
    end
endmodule

/* verilator coverage_on */

tmp/build/u337mg096_ece337_signed_multiplier_1.0.0/sim-modelsim/waveform.vcd
$date
	Wed Dec 10 03:45:28 2025
$end
$version
	QuestaSim Version 2021.4
$end
$timescale
	1ps
$end

$scope module tb_signed_multiplier $end
$var parameter 0 ! CLK_PERIOD $end
$var reg 1 " clk $end
$var reg 1 # n_rst $end
$var reg 8 $ weight [7:0] $end
$var reg 8 % value [7:0] $end
$var reg 8 & cumulative [7:0] $end
$var reg 1 ' float $end
$var reg 8 ( out [7:0] $end
$var reg 1 ) overflow $end
$var reg 1 * load $end
$var integer 32 + fail_count $end

$scope task reset_dut $end
$upscope $end

$scope task one_int_result $end
$var reg 8 , w [7:0] $end
$var reg 8 - v [7:0] $end
$var reg 8 . c [7:0] $end
$upscope $end

$scope task fp8_to_real $end
$var reg 8 / fp8 [7:0] $end
$var real 64 0 val $end
$var reg 1 1 sign $end
$var reg 4 2 exp [3:0] $end
$var reg 3 3 mant [2:0] $end
$var integer 32 4 E $end
$var real 64 5 M $end
$upscope $end

$scope task one_float_result $end
$var reg 8 6 w [7:0] $end
$var reg 8 7 v [7:0] $end
$var reg 8 8 c [7:0] $end
$var real 64 9 real_weight $end
$var real 64 : real_value $end
$var real 64 ; real_cumulative $end
$var real 64 < real_out $end
$upscope $end

$scope task test_multiplication_int $end
$var integer 32 = seed $end
$var real 64 > real_weight $end
$var real 64 ? real_value $end
$var real 64 @ real_cumulative $end
$var real 64 A real_out $end
$upscope $end

$scope task test_multiplication_float $end
$var integer 32 B seed $end
$var real 64 C real_weight $end
$var real 64 D real_value $end
$var real 64 E real_cumulative $end
$var real 64 F real_out $end
$var reg 8 G random_byte [7:0] $end
$var real 64 H error_allowed $end
$var real 64 I diff $end
$upscope $end

$scope module DUT $end
$var wire 1 J weight [7] $end
$var wire 1 K weight [6] $end
$var wire 1 L weight [5] $end
$var wire 1 M weight [4] $end
$var wire 1 N weight [3] $end
$var wire 1 O weight [2] $end
$var wire 1 P weight [1] $end
$var wire 1 Q weight [0] $end
$var wire 1 R value [7] $end
$var wire 1 S value [6] $end
$var wire 1 T value [5] $end
$var wire 1 U value [4] $end
$var wire 1 V value [3] $end
$var wire 1 W value [2] $end
$var wire 1 X value [1] $end
$var wire 1 Y value [0] $end
$var wire 1 Z cumulative [7] $end
$var wire 1 [ cumulative [6] $end
$var wire 1 \ cumulative [5] $end
$var wire 1 ] cumulative [4] $end
$var wire 1 ^ cumulative [3] $end
$var wire 1 _ cumulative [2] $end
$var wire 1 ` cumulative [1] $end
$var wire 1 a cumulative [0] $end
$var wire 1 b float $end
$var reg 8 c out [7:0] $end
$var reg 1 d overflow $end
$var reg 16 e extended_weight [15:0] $end
$var reg 16 f partial0 [15:0] $end
$var reg 16 g partial1 [15:0] $end
$var reg 16 h partial2 [15:0] $end
$var reg 16 i partial3 [15:0] $end
$var reg 16 j partial4 [15:0] $end
$var reg 16 k partial5 [15:0] $end
$var reg 16 l partial6 [15:0] $end
$var reg 16 m partial7 [15:0] $end
$var reg 16 n product [15:0] $end
$var reg 16 o sum_extended [15:0] $end
$var reg 1 p sign_cumulative $end
$var reg 1 q sign_weight $end
$var reg 1 r sign_value $end
$var reg 1 s sign_product $end
$var reg 4 t exponent_cumulative [3:0] $end
$var reg 4 u exponent_weight [3:0] $end
$var reg 4 v exponent_value [3:0] $end
$var reg 5 w exponent_product [4:0] $end
$var reg 4 x man_cumulative [3:0] $end
$var reg 4 y man_weight [3:0] $end
$var reg 4 z man_value [3:0] $end
$var reg 4 { man_out [3:0] $end
$var reg 4 | man_product [3:0] $end
$var reg 4 } final_exp [3:0] $end
$var reg 5 ~ man_sum [4:0] $end
$var reg 4 !! m_large [3:0] $end
$var reg 4 "! m_small [3:0] $end
$var reg 1 #! s_small $end
$var reg 1 $! s_large $end
$var reg 5 %! e_diff [4:0] $end
$var reg 4 &! e_out [3:0] $end
$var reg 1 '! s_out $end
$upscope $end
$upscope $end

$scope begin std $end
$upscope $end
$enddefinitions $end
#0
$dumpvars
0"
0#
bx $
bx %
bx &
x'
bx000 (
0)
x*
bx000 c
0d
bx e
b0xxxx f
b0xxxx0 g
b0xxxx00 h
b1xxx000 i
b0 j
b0 k
b0 l
b0 m
bx n
b0 o
xp
xq
xr
xs
bx t
bx u
bx v
bx w
b1xxx x
b1xxx y
b1xxx z
b1000 {
b1xxx |
bx }
bx ~
b1xxx !!
bx "!
x#!
x$!
bx %!
bx &!
x'!
bx ,
bx -
bx .
bx /
x1
bx 2
bx 3
bx 6
bx 7
bx 8
bx G
r10 !
b0 4
b0 +
b0 =
b0 B
r0 0
r0 5
r0 9
r0 :
r0 ;
r0 <
r0 >
r0 ?
r0 @
r0 A
r0 C
r0 D
r0 E
r0 F
r0.5 H
r0 I
xb
xa
x`
x_
x^
x]
x\
x[
xZ
xY
xX
xW
xV
xU
xT
xS
xR
xQ
xP
xO
xN
xM
xL
xK
xJ
$end
#5000
1"
#10000
0"
#15000
1"
#20000
0"
1#
#25000
1"
#30000
0"
#35000
1"
0*
b10001101001 =
b100101001011101110100010110 =
b1001 $
b10001000100010100010011111 =
b100 %
b10011010000010011001101001010100 =
b110100 &
0'
1Q
0P
0O
1N
0M
0L
0K
0J
0q
b1 u
b1001 y
b1001 e
0a
0`
1_
0^
1]
1\
0[
0Z
0Y
0X
1W
0V
0U
0T
0S
0R
0b
0r
b0 v
b1100 z
b110 t
b1100 x
0s
0p
b110 }
b1100 !!
0$!
0#!
b0 c
b0 {
b0 &!
b0 f
b0 g
b100100 h
b0 i
b100100 n
b1011000 o
b0 w
b0 |
b0 (
0'!
b110 %!
b0 "!
b1011000 c
b1100 ~
b1011000 (
#40000
0"
#45000
1"
#50000
0"
#55000
1"
#60000
0"
#65000
1"
#70000
b1110000110110101101100101000101 =
b11100001 $
b1010101100011010111110101000010 =
b10101011 %
b101110111010111010011111011011 =
b1011101 &
0"
0N
1L
1K
1J
1q
b1100 u
b1111111111100001 e
1s
1a
1^
0\
1[
1Y
1X
0W
1V
1T
1R
1r
b101 v
b1011 z
b1011 t
b1101 x
0s
b1011 }
b1011 %!
b1101 !!
b1111111111100001 f
b1111111111000010 g
b0 h
b1111111100001000 i
b1111110000100000 k
b1111000010000000 m
b1110101101001011 n
b1110101110101000 o
b1101 ~
b10000000 c
1d
1)
b10000000 (
#75000
1"
#80000
0"
#85000
1"
#90000
0"
#95000
1"
#100000
0"
#105000
b110010000101101000100101100000 =
b1100100 $
b11001010011001011110000111100001 =
b10010100 %
b100001111011110100111000101110 =
b1000011 &
1"
0Q
1O
0J
0q
b1100 y
b1100100 e
1s
1`
0_
0^
0]
0Y
0X
1W
0V
1U
0T
b10 v
b1100 z
b1000 t
b1011 x
b1110101110001110 o
b1000 }
b1000 %!
b1011 !!
1#!
b0 f
b0 g
b110010000 h
b0 i
b11001000000 j
b0 k
b11001000000000 m
b11100111010000 n
b11101000010011 o
b1011 ~
b1111111 c
b1111111 (
#110000
0"
#115000
1"
#120000
0"
#125000
1"
#130000
0"
#135000
1"
#140000
b10100001110001111111000011010111 =
b1000011 $
b10100101001011011100011100101100 =
b1001010 %
b1011111111100011011101000111101 =
b10111111 &
0"
1Q
1P
0O
0L
b1000 u
b1011 y
b1000011 e
1_
1^
1]
1\
0[
1Z
1X
0W
1V
0U
1S
0R
0r
b1001 v
b1010 z
b111 t
b1111 x
0s
1p
b111 }
b111 %!
b1111 !!
1$!
0#!
b10000110 g
b0 h
b1000011000 i
b0 j
b1000011000000 l
b0 m
b1001101011110 n
b1001100011101 o
1'!
b1111 ~
#145000
1"
#150000
0"
#155000
1"
#160000
0"
#165000
1"
#170000
0"
#175000
b11010101010001000011101111011010 =
b10101010 $
b1111010100001111111111110010011 =
b11110101 %
b110011101010001111110111000 =
b1100 &
1"
0Q
1N
1L
0K
1J
1q
b101 u
b1010 y
b1111111110101010 e
1s
0a
0`
0]
0\
0Z
1Y
0X
1W
0V
1U
1T
1R
1r
b1110 v
b1101 z
b1 t
b1100 x
0s
0p
b1 }
b1 %!
b1100 !!
0$!
b1111111110101010 f
b0 g
b1111111010101000 h
b0 i
b1111101010100000 j
b1111010101000000 k
b1110101010000000 l
b1101010100000000 m
b1010110110110010 n
b1010110110111110 o
0'!
b1100 ~
b10000000 c
b10000000 (
#180000
0"
#185000
1"
#190000
0"
#195000
1"
#200000
0"
#205000
1"
#210000
b111110000111101011111001011001 =
b1111100 $
b1100101000011111001001000110 =
b11001 %
b1001001010000101001000000001111 =
b10010010 &
0"
0P
1O
1M
1K
0J
0q
b1111 u
b1100 y
b1111100 e
1s
1`
0_
0^
1]
1Z
0W
1V
0T
0S
0R
0r
b11 v
b1001 z
b10 t
b1010 x
0s
1p
b10 }
b10 %!
b1010 !!
1$!
b1111100 f
b0 h
b1111100000 i
b11111000000 j
b0 k
b0 l
b0 m
b110000011100 n
b101110101110 o
1'!
b1010 ~
b1111111 c
b1111111 (
#215000
1"
#220000
0"
#225000
1"
#230000
0"
#235000
1"
#240000
0"
#245000
b10011011101011010001111100000100 =
b110111 $
b10010011001110010000101000110101 =
b100110 %
b11010100011001101101110101110010 =
b10101000 &
1"
1Q
1P
0N
0K
b110 u
b1111 y
b110111 e
0`
1^
0]
1\
0Y
1X
1W
0V
0U
1T
b100 v
b1110 z
b101 t
b1000 x
b101 }
b101 %!
b1000 !!
b0 f
b1101110 g
b11011100 h
b0 i
b0 j
b11011100000 k
b100000101010 n
b11111010010 o
b1000 ~
#250000
0"
#255000
1"
#260000
0"
#265000
1"
#270000
0"
#275000
1"
#280000
b101101000100000001111001001011 =
b1011010 $
b101101111010001000100010000 =
b1011 %
b1000011010101000111100111010001 =
b10000110 &
0"
0Q
0O
1N
0L
1K
b1011 u
b1010 y
b1011010 e
1`
1_
0^
0\
1Y
0W
1V
0T
b1 v
b1011 z
b0 t
b1110 x
b0 }
b0 %!
b0 !!
0$!
1#!
b1011010 f
b10110100 g
b0 h
b1011010000 i
b0 k
b1111011110 n
b1101100100 o
0'!
b0 ~
#285000
1"
#290000
0"
#295000
1"
#300000
0"
#305000
1"
#310000
0"
#315000
b10101110101001100010100101011110 =
b1011101 $
b1110100100001101110011001000111 =
b11101001 %
b1111111111110000000111011100 =
b11111 &
1"
1Q
0P
1O
b1101 y
b1011101 e
1a
1^
1]
0Z
0X
1T
1S
1R
1r
b1101 v
b1001 z
b11 t
b1111 x
1s
0p
b11 }
b11 %!
b1111 !!
b1111111101 o
b1011101 f
b0 g
b1011101000 i
b101110100000 k
b1011101000000 l
b10111010000000 m
b101010010100101 n
b101010011000100 o
b1111 ~
#320000
0"
#325000
1"
#330000
0"
#335000
1"
#340000
0"
#345000
1"
#350000
b11000100001010001010100100101101 =
b10001000 $
b11001110010100111100001000001010 =
b10011100 %
b111011111101101110010000000011 =
b1110111 &
0"
0Q
0O
0M
0K
1J
1q
b1 u
b1000 y
b1111111110001000 e
0s
0^
1\
1[
0Y
1W
1U
0T
0S
b11 v
b1100 z
b1110 t
b1110 }
b1110 %!
0#!
b0 f
b1111111000100000 h
b1111110001000000 i
b1111100010000000 j
b0 k
b0 l
b1100010000000000 m
b1011011011100000 n
b1011011101010111 o
b10000000 c
b10000000 (
#355000
1"
#360000
0"
#365000
1"
#370000
0"
#375000
1"
#380000
0"
#385000
b1110010010010111011110101101000 =
b11100100 $
b11100101011001111010001001001 =
b111001 %
b10110011001100000101001101110110 =
b1100110 &
1"
1O
0N
1L
1K
b1100 u
b1100 y
b1111111111100100 e
0a
0]
1Y
0W
1T
0R
0r
b111 v
b1001 z
b1100 t
b1110 x
1s
b1100 }
b1100 %!
b1110 !!
1#!
b1111111111100100 f
b0 h
b1111111100100000 i
b1111111001000000 j
b1111110010000000 k
b0 m
b1111100111000100 n
b1111101000101010 o
b1110 ~
#390000
0"
#395000
1"
#400000
0"
#405000
1"
#410000
0"
#415000
1"
#420000
b1000101011001011101001101111111 =
b10001010 $
b10010001110001101100111110110100 =
b100011 %
b10100100011101000111011100100101 =
b1001000 &
0"
1P
0O
1N
0L
0K
b1 u
b1010 y
b1111111110001010 e
0`
0_
1^
0\
1X
0V
0U
b100 v
b1011 z
b1001 t
b1000 x
b1001 }
b1001 %!
b1000 !!
b1111111110001010 f
b1111111100010100 g
b0 i
b0 j
b1111000101000000 k
b1110111111011110 n
b1111000000100110 o
b1000 ~
#425000
1"
#430000
0"
#435000
1"
#440000
0"
#445000
1"
#450000
0"
#455000
b10010011101010100100110100010 =
b100100 $
b110010010110011000010111011 =
b1100 %
b1100011010101000010011000000 =
b11000 &
1"
0P
1O
0N
1L
0J
0q
b100 u
b1100 y
b100100 e
0s
1]
0[
0Y
0X
1W
1V
0T
b1 v
b1100 z
b11 t
b11 }
b11 %!
0#!
b0 f
b0 g
b10010000 h
b100100000 i
b0 k
b110110000 n
b111001000 o
b1111111 c
b1111111 (
#460000
0"
#465000
1"
#470000
0"
#475000
1"
#480000
0"
#485000
1"
#490000
b11011110110010100000110111000001 =
b10111101 $
b10111000010000001101000010001110 =
b1110000 %
b10100111000011000011011110110111 =
b1001110 &
0"
1Q
1N
1M
1J
1q
b111 u
b1101 y
b1111111110111101 e
1s
1`
1_
0]
1[
0W
0V
1U
1T
1S
b1110 v
b1000 z
b1001 t
b1110 x
b1001 }
b1001 %!
b1110 !!
1#!
b0 h
b0 i
b1111101111010000 j
b1111011110100000 k
b1110111101000000 l
b1110001010110000 n
b1110001011111110 o
b1110 ~
b10000000 c
b10000000 (
#495000
1"
#500000
0"
#505000
1"
#510000
0"
#515000
1"
#520000
0"
#525000
b10011011010100111110100010001100 =
b110110 $
b10001101100011000101010000011101 =
b11011 %
b11001101110000011101010000111010 =
b10011011 &
1"
0Q
1P
0N
0J
0q
b110 u
b1110 y
b110110 e
0s
1a
0_
1]
0[
1Z
1Y
1X
1V
0T
0S
b11 v
b1011 z
b11 t
b1011 x
1p
b11 }
b11 %!
b1011 !!
1$!
0#!
b110110 f
b1101100 g
b110110000 i
b1101100000 j
b0 k
b0 l
b10110110010 n
b10101001101 o
1'!
b1011 ~
b1111111 c
b1111111 (
#530000
0"
#535000
1"
#540000
0"
#545000
1"
#550000
0"
#555000
1"
#560000
b1110000001101111110010001110011 =
b11100000 $
b10010111110011101100011100011000 =
b101111 %
b11010111110010011010011000111001 =
b10101111 &
0"
0P
0O
0M
1K
1J
1q
b1100 u
b1000 y
b1111111111100000 e
1s
1_
0]
1\
1W
0U
1T
b101 v
b1111 z
b101 t
b1111 x
b101 }
b101 %!
b1111 !!
1#!
b1111111111100000 f
b1111111111000000 g
b1111111110000000 h
b1111111100000000 i
b0 j
b1111110000000000 k
b1111101000100000 n
b1111100111001111 o
b1111 ~
b10000000 c
b10000000 (
#565000
1"
#570000
0"
#575000
1"
#580000
0"
#585000
1"
#590000
0"
#595000
b10110000001001000000000010100110 =
b1100000 $
b11100001100000101111001011101111 =
b11000011 %
b101111001000011010110001100100 =
b1011110 &
1"
0J
0q
b1100000 e
0s
0a
1]
0\
1[
0Z
0W
0V
0T
1S
1R
1r
b1000 v
b1011 z
b1011 t
b1110 x
1s
0p
b1111101001111110 o
b1011 }
b1011 %!
b1110 !!
0$!
b1100000 f
b11000000 g
b0 h
b0 i
b0 k
b1100000000000 l
b11000000000000 m
b100100100100000 n
0'!
b100100101111110 o
b1110 ~
b1111111 c
b1111111 (
#600000
0"
#605000
1"
#610000
0"
#615000
1"
#620000
0"
#625000
1"
#630000
b100000000111000010000000010101 =
b1000000 $
b1000100001110111100000111010010 =
b10001000 %
b1101110100000111101111100101011 =
b11011101 &
0"
0L
b1000 u
b1000000 e
1a
0`
1Z
0Y
0X
1V
0S
b1 v
b1000 z
b1101 x
1p
b1101 !!
1$!
b0 f
b0 g
b1000000000 i
b0 l
b10000000000000 m
b10001000000000 n
b10000111011101 o
1'!
b1101 ~
#635000
1"
#640000
0"
#645000
1"
#650000
0"
#655000
1"
#660000
0"
#665000
b10001000110011110010001110000 =
b100010 $
b11100110110001011001110110110001 =
b11001101 %
b1110010111100100100001110111110 =
b11100101 &
1"
1P
1L
0K
b100 u
b1010 y
b100010 e
0^
0]
1\
1Y
1W
1S
b1001 v
b1101 z
b1100 t
b1100 }
b1100 %!
b100010 f
b10001000 h
b100010000 i
b100010000000 l
b1000100000000 m
b1101100111010 n
b1101100011111 o
#670000
0"
#675000
1"
#680000
0"
#685000
1"
#690000
0"
#695000
1"
#700000
b10011101001011101110010100100111 =
b111010 $
b100101010101110111101100111100 =
b1001010 %
b11010011100010111011101100001101 =
b10100111 &
0"
1N
1M
b111 u
b111010 e
1`
0[
0Y
1X
0W
0R
0r
b1010 z
b100 t
b1111 x
0s
b100 }
b100 %!
b1111 !!
0#!
b0 f
b1110100 g
b0 h
b111010000 i
b111010000000 l
b0 m
b1000011000100 n
b1000001101011 o
b1111 ~
#705000
1"
#710000
0"
#715000
1"
#720000
0"
#725000
1"
#730000
0"
#735000
b111010011100010111001001101010 =
b1110100 $
b10000100100000000011100011 =
b100 %
b10010011010110010011110011001000 =
b100110 &
1"
0P
1O
0N
1K
b1110 u
b1100 y
b1110100 e
0a
0Z
0X
1W
0V
0S
b0 v
b1100 z
b1110 x
0p
b1110 !!
0$!
b0 g
b111010000 h
b0 i
b0 l
b111010000 n
b111110110 o
0'!
b1110 ~
#740000
0"
#745000
1"
#750000
0"
#755000
1"
#760000
0"
#765000
1"
